floky-0.2.2.dist-info/METADATA
floky-0.2.2.dist-info/WHEEL
floky/__init__.py
floky/stats.py
floky/floky.cpython-36m-x86_64-linux-gnu.so
floky-0.2.2.dist-info/RECORD
